lnschema_drylab/__init__.py
lnschema_drylab/_core.py
lnschema_drylab/_id.py
lnschema_drylab/_type.py
lnschema_drylab/id.py
lnschema_drylab/type.py
lnschema_drylab-0.1.0.dist-info/LICENSE
lnschema_drylab-0.1.0.dist-info/WHEEL
lnschema_drylab-0.1.0.dist-info/METADATA
lnschema_drylab-0.1.0.dist-info/RECORD
