Metadata-Version: 2.1
Name: lnschema_drylab
Version: 0.1.0
Summary: Schema module drylab (`xqfj`).
Author-email: Lamin Labs <laminlabs@gmail.com>
Requires-Dist: nbproject
Requires-Dist: lnschema_core
Requires-Dist: sqlmodel
Requires-Dist: pre-commit ; extra == "dev"
Requires-Dist: nox ; extra == "dev"
Requires-Dist: pytest>=6.0 ; extra == "test"
Requires-Dist: pytest-cov ; extra == "test"
Project-URL: Home, https://github.com/laminlabs/lnschema-drylab
Provides-Extra: dev
Provides-Extra: test
